ImageHorizonLibrary/__init__.py
ImageHorizonLibrary/errors.py
ImageHorizonLibrary/utils.py
ImageHorizonLibrary/version.py
ImageHorizonLibrary/interaction/__init__.py
ImageHorizonLibrary/interaction/_keyboard.py
ImageHorizonLibrary/interaction/_mouse.py
ImageHorizonLibrary/interaction/_operating_system.py
ImageHorizonLibrary/recognition/__init__.py
ImageHorizonLibrary/recognition/_recognize_images.py
ImageHorizonLibrary/recognition/_screenshot.py
robotframework_imagehorizonlibrary-1.0.dist-info/LICENSE
robotframework_imagehorizonlibrary-1.0.dist-info/METADATA
robotframework_imagehorizonlibrary-1.0.dist-info/WHEEL
robotframework_imagehorizonlibrary-1.0.dist-info/top_level.txt
robotframework_imagehorizonlibrary-1.0.dist-info/RECORD
