Metadata-Version: 2.1
Name: robotframework-imagehorizonlibrary
Version: 1.0
Summary: Cross-platform Robot Framework library for GUI automation based on image recognition
Home-page: https://github.com/Eficode/robotframework-imagehorizonlibrary
Author: Eficode Oy
Author-email: info@eficode.com
License: MIT
Keywords: imagerecognition gui robotframework testing testautomation acceptancetesting atdd bdd
Platform: UNKNOWN
Classifier: Development Status :: 5 - Production/Stable
Classifier: Programming Language :: Python :: 3 :: Only
Classifier: Operating System :: OS Independent
Classifier: Topic :: Software Development :: Testing
Classifier: License :: OSI Approved :: MIT License
Requires-Dist: robotframework (>=2.8)
Requires-Dist: pyautogui (>=0.9.30)
